sciservices/__init__.py
sciservices/auth.py
sciservices/settings.py
sciservices/urls.py
sciservices/wsgi.py
sciservices-0.1.1.dist-info/DESCRIPTION.rst
sciservices-0.1.1.dist-info/METADATA
sciservices-0.1.1.dist-info/RECORD
sciservices-0.1.1.dist-info/WHEEL
sciservices-0.1.1.dist-info/metadata.json
sciservices-0.1.1.dist-info/top_level.txt
